PolarGeosAI/MultiInputModel.py
PolarGeosAI/__init__.py
PolarGeosAI/func.py
PolarGeosAI/func_ml.py
PolarGeosAI/impl.py
PolarGeosAI/run_function.py
PolarGeosAI/test_function.py
polargeosai-0.0.1.dist-info/METADATA
polargeosai-0.0.1.dist-info/WHEEL
polargeosai-0.0.1.dist-info/licenses/LICENSE.txt
polargeosai-0.0.1.dist-info/RECORD
