Metadata-Version: 2.4
Name: PolarGeosAI
Version: 0.0.1
Summary: Easy extraction and processing of matching GOES geostationary satellite and polar orbiting scatterometer data for model training.
Project-URL: Homepage, https://yongxingloo.github.io/PolarGeosAIDocs/
Project-URL: Issues, https://github.com/yongxingloo/PolarGeosAI/issues
Author-email: Yongxing Loo  <looyongxing@gmail.com>
License-File: LICENSE.txt
Classifier: License :: OSI Approved :: MIT License
Classifier: Operating System :: OS Independent
Classifier: Programming Language :: Python :: 3
Requires-Python: >=3.8
Requires-Dist: fsspec
Requires-Dist: h5netcdf
Requires-Dist: matplotlib
Requires-Dist: netcdf4
Requires-Dist: numpy
Requires-Dist: pandas
Requires-Dist: pysolar
Requires-Dist: s3fs
Requires-Dist: scikit-learn
Requires-Dist: torch
Requires-Dist: tqdm
Requires-Dist: xarray
